{"GlobalPropertiesHash":"xQVK3XeBg8351PRkzy07ZOusY648tO9axcSpJVDhsGY=","FingerprintPatternsHash":"gq3WsqcKBUGTSNle7RKKyXRIwh7M8ccEqOqYvIzoM04=","PropertyOverridesHash":"8ZRc1sGeVrPBx4lD717BgRaQekyh78QKV9SKsdt638U=","InputHashes":["rN\u002B2vge5BcdJ0Dzzt\u002BMkKy6ElsH\u002BhrJ55zRQsbMjZB8=","/r4n8KZAfj9Icl2mirO5xQQByG31RtmdbR2mhPAV3is=","RndaCW4N9JP5nUKa5MIPUNn7/SKyLcemiuSTnBiS7lk=","lRJKSpr8rHi/HMnAnqLG6GJpkUxUtaor0PsTE/MKvgU=","Ub5bLxsBSWuaf/A5lIlIn3Il1R1inKyPjUTD8TYoO24=","T9dLYVn69PzY6KkDHrwjC5V2pEksf/cdHnd2UDxRjOQ=","WvRoMEpbV84wIm5K\u002Blq7GmGeoJHnnPpnDKLpzsHCsLM=","6RWJL8toeYTXaICP\u002Bzd7C/Oe3SsjQLqVqeBs6VznoRo=","BN6tqSEFl9AkvRCFsoE04KO4iLR9auIs6etWeVh79Hk=","rYCrqcJmQpiVnRvRFREmJmnV\u002Bz3CJxtuDMVRTQGZhvg=","g\u002BqUDZPWB1embo4qXo/n/npKRXDJS88az6OOVxPsGgs=","6MO4/hcMLL3ILaNbDgtfJyqoUBe8iEdRnQlmb2ws\u002BM4=","VTmiBqZcbA01sNYYPt4tmhj/iGnMvFx/6IlBKjwFgW0=","/lN6zWONLU8w919WPnWOwZo/IlbB6LtjnXF/uefPOUU=","esXl6gg/jo9BmeL44c1vOpHWPkG7kr61zLqXPM5i/F8=","tvxlEolXjgQNxnXF7GuazZQ/CK1T0JutGNgkG\u002B94v7M=","i7qS\u002Br0aFfirPFXxtr8Dzz22aXz9kprQYxMwBzUv\u002BTs=","/u65kinqUvQFmSeWO5i5Lg0YAjO9nA3/Tzm94HmXKyo=","9UULi4b8/TvNnRaP1A/fJNh6OxeOBWmN5onsrQ7897o=","\u002Bu\u002BLnfoj5jMWjSvUPgmK1auSgv3oGs5bWG2OIvohHZ4="],"CachedAssets":{"rN\u002B2vge5BcdJ0Dzzt\u002BMkKy6ElsH\u002BhrJ55zRQsbMjZB8=":{"Identity":"C:\\Users\\Fring\\Documents\\Progetti Personali\\IlMioPortfolio\\wwwroot\\app.css","SourceId":"IlMioPortfolio","SourceType":"Discovered","ContentRoot":"C:\\Users\\Fring\\Documents\\Progetti Personali\\IlMioPortfolio\\wwwroot\\","BasePath":"_content/IlMioPortfolio","RelativePath":"app#[.{fingerprint}]?.css","AssetKind":"All","AssetMode":"All","AssetRole":"Primary","AssetMergeBehavior":null,"AssetMergeSource":"","RelatedAsset":null,"AssetTraitName":null,"AssetTraitValue":null,"Fingerprint":"1bvjt7tool","Integrity":"Pa5WSk/SUgBLbeFp\u002BmJqO2ehVHk/bLoPImG4y\u002BkT53o=","CopyToOutputDirectory":"Never","CopyToPublishDirectory":"PreserveNewest","OriginalItemSpec":"wwwroot\\app.css","FileLength":343,"LastWriteTime":"2025-08-02T20:01:31.4988729+00:00"},"/r4n8KZAfj9Icl2mirO5xQQByG31RtmdbR2mhPAV3is=":{"Identity":"C:\\Users\\Fring\\Documents\\Progetti Personali\\IlMioPortfolio\\wwwroot\\bootstrap\\bootstrap.min.css","SourceId":"IlMioPortfolio","SourceType":"Discovered","ContentRoot":"C:\\Users\\Fring\\Documents\\Progetti Personali\\IlMioPortfolio\\wwwroot\\","BasePath":"_content/IlMioPortfolio","RelativePath":"bootstrap/bootstrap.min#[.{fingerprint}]?.css","AssetKind":"All","AssetMode":"All","AssetRole":"Primary","AssetMergeBehavior":null,"AssetMergeSource":"","RelatedAsset":null,"AssetTraitName":null,"AssetTraitValue":null,"Fingerprint":"bpk8xqwxhs","Integrity":"z8OR40MowJ8GgK6P89Y\u002BhiJK5\u002BcclzFHzLhFQLL92bg=","CopyToOutputDirectory":"Never","CopyToPublishDirectory":"PreserveNewest","OriginalItemSpec":"wwwroot\\bootstrap\\bootstrap.min.css","FileLength":162720,"LastWriteTime":"2025-08-02T00:19:27.0502102+00:00"},"RndaCW4N9JP5nUKa5MIPUNn7/SKyLcemiuSTnBiS7lk=":{"Identity":"C:\\Users\\Fring\\Documents\\Progetti Personali\\IlMioPortfolio\\wwwroot\\bootstrap\\bootstrap.min.css.map","SourceId":"IlMioPortfolio","SourceType":"Discovered","ContentRoot":"C:\\Users\\Fring\\Documents\\Progetti Personali\\IlMioPortfolio\\wwwroot\\","BasePath":"_content/IlMioPortfolio","RelativePath":"bootstrap/bootstrap.min.css#[.{fingerprint}]?.map","AssetKind":"All","AssetMode":"All","AssetRole":"Primary","AssetMergeBehavior":null,"AssetMergeSource":"","RelatedAsset":null,"AssetTraitName":null,"AssetTraitValue":null,"Fingerprint":"8inm30yfxf","Integrity":"gBwg2tmA0Ci2u54gMF1jNCVku6vznarkLS6D76htNNQ=","CopyToOutputDirectory":"Never","CopyToPublishDirectory":"PreserveNewest","OriginalItemSpec":"wwwroot\\bootstrap\\bootstrap.min.css.map","FileLength":449111,"LastWriteTime":"2025-08-02T00:19:27.0526067+00:00"},"lRJKSpr8rHi/HMnAnqLG6GJpkUxUtaor0PsTE/MKvgU=":{"Identity":"C:\\Users\\Fring\\Documents\\Progetti Personali\\IlMioPortfolio\\wwwroot\\favicon.png","SourceId":"IlMioPortfolio","SourceType":"Discovered","ContentRoot":"C:\\Users\\Fring\\Documents\\Progetti Personali\\IlMioPortfolio\\wwwroot\\","BasePath":"_content/IlMioPortfolio","RelativePath":"favicon#[.{fingerprint}]?.png","AssetKind":"All","AssetMode":"All","AssetRole":"Primary","AssetMergeBehavior":null,"AssetMergeSource":"","RelatedAsset":null,"AssetTraitName":null,"AssetTraitValue":null,"Fingerprint":"ifv42okdf2","Integrity":"4mWsDy3aHl36ZbGt8zByK7Pvd4kRUoNgTYzRnwmPHwg=","CopyToOutputDirectory":"Never","CopyToPublishDirectory":"PreserveNewest","OriginalItemSpec":"wwwroot\\favicon.png","FileLength":1148,"LastWriteTime":"2025-08-02T00:19:26.9662277+00:00"}},"CachedCopyCandidates":{}}